JVG
