Metadata-Version: 2.1
Name: JVectorGraph
Version: 0.1.8
Summary: JVectorGraph
Author: Jakub Kubis
Author-email: jbiosystem@gmail.com
License: MIT
Keywords: vector,graph,svg,png,mpl,jpeg
Classifier: Development Status :: 3 - Alpha
Classifier: Programming Language :: Python :: 3
Classifier: Operating System :: MacOS :: MacOS X
Classifier: Operating System :: Microsoft :: Windows
Classifier: Operating System :: POSIX :: Linux
Requires-Python: >=3.7
